hMailServerConsole/__init__.py
hMailServerConsole/test1.py
hMailServerConsole-0.0.1.dist-info/LICENSE.txt
hMailServerConsole-0.0.1.dist-info/METADATA
hMailServerConsole-0.0.1.dist-info/WHEEL
hMailServerConsole-0.0.1.dist-info/entry_points.txt
hMailServerConsole-0.0.1.dist-info/top_level.txt
hMailServerConsole-0.0.1.dist-info/RECORD
