Metadata-Version: 2.1
Name: hMailServerConsole
Version: 0.0.1
Summary: hMailServerConsole
Home-page: https://github.com/LoveNishimiyaShouko/hMailServerConsole
Author: LoveNishimiyaShouko
Author-email: LoveNishimiyaShouko@LoveNishimiyaShouko.LoveNishimiyaShouko
License: AGPLv3
Project-URL: Documentation, https://github.com/LoveNishimiyaShouko/hMailServerConsole/tree/main/docs
Project-URL: Source, https://github.com/LoveNishimiyaShouko/hMailServerConsole/tree/main/code
Keywords: NishimiyaShouko,LoveNishimiya,Nishimiya,LoveNishimiya,Shouko,hMailServerConsole
Platform: UNKNOWN
Classifier: Development Status :: 5 - Production/Stable
Classifier: License :: OSI Approved :: GNU Affero General Public License v3 or later (AGPLv3+)
Classifier: Operating System :: OS Independent
Classifier: Programming Language :: Python
Requires-Python: >=3
Requires-Dist: requests
